streamlit_server_state/__init__.py
streamlit_server_state/_compat.py
streamlit_server_state/app_context.py
streamlit_server_state/hash.py
streamlit_server_state/rerun.py
streamlit_server_state/rerun_suppression.py
streamlit_server_state/server.py
streamlit_server_state/server_state.py
streamlit_server_state/server_state_item.py
streamlit_server_state/server_state_lock.py
streamlit_server_state/session_info.py
streamlit_server_state-0.20.1.dist-info/METADATA
streamlit_server_state-0.20.1.dist-info/WHEEL
streamlit_server_state-0.20.1.dist-info/licenses/LICENSE
streamlit_server_state-0.20.1.dist-info/RECORD
