Metadata-Version: 2.4
Name: streamlit-server-state
Version: 0.20.1
Project-URL: Homepage, https://github.com/whitphx/streamlit-server-state
Author-email: "Yuichiro Tachibana (Tsuchiya)" <t.yic.yt@gmail.com>
License: MIT License
License-File: LICENSE
Requires-Python: >=3.9
Requires-Dist: packaging>=20.0
Requires-Dist: streamlit>=0.65.0
